README.md
setup.cfg
setup.py
cbpro/__init__.py
cbpro/authenticated_client.py
cbpro/cbpro_auth.py
cbpro/order_book.py
cbpro/public_client.py
cbpro/websocket_client.py
cbpro2.egg-info/PKG-INFO
cbpro2.egg-info/SOURCES.txt
cbpro2.egg-info/dependency_links.txt
cbpro2.egg-info/requires.txt
cbpro2.egg-info/top_level.txt